nonebot_plugin_admin/__init__.py
nonebot_plugin_admin/admin.py
nonebot_plugin_admin/admin_role.py
nonebot_plugin_admin/approve.py
nonebot_plugin_admin/auto_ban.py
nonebot_plugin_admin/broadcast.py
nonebot_plugin_admin/config.py
nonebot_plugin_admin/func_hook.py
nonebot_plugin_admin/group_msg.py
nonebot_plugin_admin/group_recall.py
nonebot_plugin_admin/group_request_verify.py
nonebot_plugin_admin/img_check.py
nonebot_plugin_admin/kick_member_by_rule.py
nonebot_plugin_admin/message.py
nonebot_plugin_admin/notice.py
nonebot_plugin_admin/particular_e_notice.py
nonebot_plugin_admin/path.py
nonebot_plugin_admin/request_manual.py
nonebot_plugin_admin/requests.py
nonebot_plugin_admin/switcher.html
nonebot_plugin_admin/switcher.py
nonebot_plugin_admin/utils.py
nonebot_plugin_admin/word_analyze.py
nonebot_plugin_admin/wordcloud.py
nonebot_plugin_admin/util/__init__.py
nonebot_plugin_admin/util/file_util.py
nonebot_plugin_admin/util/time_util.py
nonebot_plugin_admin-0.4.7.dist-info/LICENSE
nonebot_plugin_admin-0.4.7.dist-info/METADATA
nonebot_plugin_admin-0.4.7.dist-info/WHEEL
nonebot_plugin_admin-0.4.7.dist-info/top_level.txt
nonebot_plugin_admin-0.4.7.dist-info/RECORD
