Metadata-Version: 2.1
Name: nonebot-plugin-admin
Version: 0.4.7
Summary: nonebot2 plugin for group administration
Home-page: https://github.com/yzyyz1387/nonebot_plugin_admin
Author: yzyyz1387
Author-email: youzyyz1384@qq.com
Keywords: pip,nonebot2,nonebot,admin,nonebot_plugin
Platform: any
Classifier: Programming Language :: Python :: 3
Classifier: License :: OSI Approved :: GNU Affero General Public License v3 or later (AGPLv3+)
Classifier: Operating System :: OS Independent
License-File: LICENSE
Requires-Dist: fuzzyfinder
Requires-Dist: nonebot-adapter-onebot>=2.0.0-beta.1
Requires-Dist: nonebot2>=2.0.0-beta.4
Requires-Dist: jieba
Requires-Dist: httpx
Requires-Dist: tencentcloud-sdk-python>=3.0.580
Requires-Dist: jinja2
Requires-Dist: pyppeteer
Requires-Dist: imageio
Requires-Dist: numpy
Requires-Dist: nonebot_plugin_apscheduler
